fine/__init__.py
fine/activations/__init__.py
fine/activations/Softmax.py
fine/activations/Linear.py
fine/activations/Sigmoid.py
fine/activations/ReLU.py
fine/datasets/mnist_data.py
fine/datasets/__init__.py
fine/datasets/cifar_data.py
fine/models/__init__.py
fine/models/Sequential.py
fine/models/model_utils/Input.py
fine/models/model_utils/__init__.py
fine/models/model_utils/accuracy/Accuracy.py
fine/models/model_utils/accuracy/Regression.py
fine/models/model_utils/accuracy/__init__.py
fine/models/model_utils/accuracy/Categorical.py
fine/utils/im2col_cython.cpython-39-x86_64-linux-gnu.so
fine/utils/__init__.py
fine/utils/augment_image.py
fine/utils/download_file.py
fine/utils/im2col/im2col.py
fine/loss/BinaryCrossEntropy.py
fine/loss/CategoricalCrossEntropy.py
fine/loss/__init__.py
fine/loss/Loss.py
fine/loss/MeanSquaredError.py
fine/optimizers/__init__.py
fine/optimizers/StochasticGD.py
fine/optimizers/Adam.py
fine/layers/Dense.py
fine/layers/Dropout.py
fine/layers/__init__.py
fine/layers/Conv2D.py
fine/layers/Flatten.py
fine/layers/MaxPool2D.py
deep_fine-0.1.0.dist-info/METADATA
deep_fine-0.1.0.dist-info/WHEEL
deep_fine-0.1.0.dist-info/RECORD
deep_fine-0.1.0.dist-info/top_level.txt
